<annotation><filename>00005977_010</filename><size><width>1024</width><height>1024</height><depth>3</depth></size><object><name>nodule</name><pose>Unspecified</pose><truncated>0</truncated><difficult>0</difficult><bndbox><xmin>169</xmin><ymin>284</ymin><xmax>250</xmax><ymax>366</ymax></bndbox></object><object><name>nodule</name><pose>Unspecified</pose><truncated>0</truncated><difficult>0</difficult><bndbox><xmin>190</xmin><ymin>500</ymin><xmax>259</xmax><ymax>576</ymax></bndbox></object><object><name>nodule</name><pose>Unspecified</pose><truncated>0</truncated><difficult>0</difficult><bndbox><xmin>120</xmin><ymin>752</ymin><xmax>191</xmax><ymax>828</ymax></bndbox></object><object><name>nodule</name><pose>Unspecified</pose><truncated>0</truncated><difficult>0</difficult><bndbox><xmin>76</xmin><ymin>815</ymin><xmax>146</xmax><ymax>891</ymax></bndbox></object></annotation>