<annotation><filename>00015892_005</filename><size><width>1024</width><height>1024</height><depth>3</depth></size><object><name>nodule</name><pose>Unspecified</pose><truncated>0</truncated><difficult>0</difficult><bndbox><xmin>332</xmin><ymin>626</ymin><xmax>438</xmax><ymax>729</ymax></bndbox></object><object><name>nodule</name><pose>Unspecified</pose><truncated>0</truncated><difficult>0</difficult><bndbox><xmin>683</xmin><ymin>618</ymin><xmax>784</xmax><ymax>722</ymax></bndbox></object><object><name>nodule</name><pose>Unspecified</pose><truncated>0</truncated><difficult>0</difficult><bndbox><xmin>742</xmin><ymin>336</ymin><xmax>796</xmax><ymax>383</ymax></bndbox></object><object><name>nodule</name><pose>Unspecified</pose><truncated>0</truncated><difficult>0</difficult><bndbox><xmin>767</xmin><ymin>397</ymin><xmax>825</xmax><ymax>443</ymax></bndbox></object><object><name>nodule</name><pose>Unspecified</pose><truncated>0</truncated><difficult>0</difficult><bndbox><xmin>798</xmin><ymin>555</ymin><xmax>866</xmax><ymax>625</ymax></bndbox></object></annotation>